CCFToolkit/__init__.py
CCFToolkit/ccf_toolkit.py
CCFToolkit-1.0.0.dist-info/METADATA
CCFToolkit-1.0.0.dist-info/WHEEL
CCFToolkit-1.0.0.dist-info/top_level.txt
CCFToolkit-1.0.0.dist-info/RECORD
