Metadata-Version: 2.1
Name: CCFToolkit
Version: 1.0.0
Summary: A toolkit for reading and generating Paintman CCF files for color chart management.
Home-page: https://github.com/ChenxingM/CCFToolkit
Author: Ma Chenxing
Author-email: tammcx@gmail.com
Classifier: Programming Language :: Python :: 3
Classifier: License :: OSI Approved :: MIT License
Classifier: Operating System :: OS Independent
Requires-Python: >=3.6
